[
  {
    "patternId": "ACC_INV_001",
    "subjectId": "ACC",
    "chapterId": "ACC_INV",
    "name": "기말재고 포함 여부 판단",
    "type": "calculation",
    "grade": "S",
    "frequency": 5,
    "years": [2018, 2020, 2023, 2024, 2025],
    "difficulty": "medium",
    "importance": 95,
    "description": "회계기간 말 재고자산에 포함할 품목과 제외할 품목을 판단하는 패턴. 위탁·임가공·운송 중 재화의 소유권 귀속 시점을 확인한다.",
    "coreConcept": "재고자산은 기업이 소유권을 보유한 미판매 재화·제품·원재료·재공품이다.",
    "relatedPatterns": ["ACC_INV_002", "ACC_INV_003"],
    "relatedQuestions": ["ACC_INV_Q001", "ACC_INV_Q002", "ACC_INV_Q003"]
  },
  {
    "patternId": "ACC_INV_002",
    "subjectId": "ACC",
    "chapterId": "ACC_INV",
    "name": "FOB/CIF 조건에 따른 재고 귀속",
    "type": "calculation",
    "grade": "S",
    "frequency": 4,
    "years": [2019, 2021, 2022, 2025],
    "difficulty": "hard",
    "importance": 92,
    "description": "매입·매출 거래에서 FOB Shipping Point/Destination, CIF 조건에 따라 재고와 매출원가 귀속 시점을 판단한다.",
    "coreConcept": "FOB Shipping Point는 선적 시점에 소유권 이전, FOB Destination은 도착 시점에 소유권 이전.",
    "relatedPatterns": ["ACC_INV_001", "ACC_INV_003"],
    "relatedQuestions": ["ACC_INV_Q004", "ACC_INV_Q005"]
  },
  {
    "patternId": "ACC_INV_003",
    "subjectId": "ACC",
    "chapterId": "ACC_INV",
    "name": "운반비·보험료 처리와 재고 귀속",
    "type": "journalEntry",
    "grade": "A",
    "frequency": 3,
    "years": [2020, 2022, 2024],
    "difficulty": "medium",
    "importance": 78,
    "description": "매입 관련 운반비·하역비·보험료를 재고원가에 포함할지 당기비용 처리할지 판단한다.",
    "coreConcept": "재고 취득에 직접 관련된 부대비용은 재고원가에 가산한다.",
    "relatedPatterns": ["ACC_INV_002", "ACC_INV_004"],
    "relatedQuestions": ["ACC_INV_Q006", "ACC_INV_Q007"]
  },
  {
    "patternId": "ACC_INV_004",
    "subjectId": "ACC",
    "chapterId": "ACC_INV",
    "name": "매출원가 계산 (PER법)",
    "type": "calculation",
    "grade": "S",
    "frequency": 6,
    "years": [2018, 2019, 2021, 2023, 2025],
    "difficulty": "medium",
    "importance": 90,
    "description": "기초재고 + 당기매입 - 기말재고 = 매출원가 공식을 이용한 계산 패턴.",
    "coreConcept": "PER(주기적) 재고조사법에서 매출원가는 기말재고 역산으로 구한다.",
    "relatedPatterns": ["ACC_INV_005", "ACC_INV_006"],
    "relatedQuestions": ["ACC_INV_Q008", "ACC_INV_Q009", "ACC_INV_Q010"]
  },
  {
    "patternId": "ACC_INV_005",
    "subjectId": "ACC",
    "chapterId": "ACC_INV",
    "name": "PER vs PR 재고조사법",
    "type": "concept",
    "grade": "A",
    "frequency": 2,
    "years": [2019, 2023],
    "difficulty": "easy",
    "importance": 72,
    "description": "주기적 재고조사법(PER)과 실지 재고조사법(PR)의 차이와 적용 시점을 구분한다.",
    "coreConcept": "PER는 연중 장부기록 유지 후 기말 실사, PR은 매입·매출 시마다 잔액 확인.",
    "relatedPatterns": ["ACC_INV_004"],
    "relatedQuestions": ["ACC_INV_Q011"]
  },
  {
    "patternId": "ACC_INV_006",
    "subjectId": "ACC",
    "chapterId": "ACC_INV",
    "name": "FIFO·총평균법 매출원가",
    "type": "calculation",
    "grade": "A",
    "frequency": 4,
    "years": [2020, 2021, 2023, 2024],
    "difficulty": "hard",
    "importance": 85,
    "description": "선입선출법(FIFO)과 총평균법으로 매출원가와 기말재고를 계산한다.",
    "coreConcept": "FIFO는 먼저 매입한 원가부터 매출원가로 인식, 총평균법은 가중평균 단가 적용.",
    "relatedPatterns": ["ACC_INV_004", "ACC_INV_007"],
    "relatedQuestions": ["ACC_INV_Q012", "ACC_INV_Q013"]
  },
  {
    "patternId": "ACC_INV_007",
    "subjectId": "ACC",
    "chapterId": "ACC_INV",
    "name": "LCM(순실현가능가치) 평가",
    "type": "calculation",
    "grade": "A",
    "frequency": 3,
    "years": [2018, 2022, 2025],
    "difficulty": "medium",
    "importance": 80,
    "description": "재고자산을 취득원가와 순실현가능가치 중 낮은 금액(LCM)으로 평가한다.",
    "coreConcept": "순실현가능가치 = 순매가액 - 추가원가. LCM 적용 시 재고자산 감소손실 인식.",
    "relatedPatterns": ["ACC_INV_006"],
    "relatedQuestions": ["ACC_INV_Q014", "ACC_INV_Q015"]
  },
  {
    "patternId": "ACC_INV_008",
    "subjectId": "ACC",
    "chapterId": "ACC_INV",
    "name": "재고자산 관련 분개",
    "type": "journalEntry",
    "grade": "B",
    "frequency": 2,
    "years": [2021, 2024],
    "difficulty": "medium",
    "importance": 65,
    "description": "재고자산 취득·매출·평가손·재고감모손 등 재고자산 관련 분개를 작성한다.",
    "coreConcept": "재고자산 증감은 자산 계정과 매출원가·매입 계정의 대응으로 처리한다.",
    "relatedPatterns": ["ACC_INV_003", "ACC_INV_007"],
    "relatedQuestions": ["ACC_INV_Q016"]
  }
]
